mangokit/__init__.py
mangokit/method.py
mangokit/apidrive/__init__.py
mangokit/apidrive/_async_request.py
mangokit/apidrive/_sync_request.py
mangokit/assertion/__init__.py
mangokit/assertion/_custom_assertion.py
mangokit/assertion/_public_assertion.py
mangokit/assertion/_sql_assertion.py
mangokit/data_processor/__init__.py
mangokit/data_processor/_cache_tool.py
mangokit/data_processor/_coding_tool.py
mangokit/data_processor/_encryption_tool.py
mangokit/data_processor/_json_tool.py
mangokit/data_processor/_random_character_info_data.py
mangokit/data_processor/_random_number_data.py
mangokit/data_processor/_random_string_data.py
mangokit/data_processor/_random_time_data.py
mangokit/data_processor/_sql_cache.py
mangokit/database/__init__.py
mangokit/database/_mysql_connect.py
mangokit/database/_sqlite_connect.py
mangokit/decorator/__init__.py
mangokit/decorator/convert_args.py
mangokit/decorator/inject_to_class.py
mangokit/decorator/method_callback.py
mangokit/decorator/retry.py
mangokit/decorator/singleton.py
mangokit/enums/__init__.py
mangokit/enums/_base_enum.py
mangokit/enums/_enums.py
mangokit/enums/_ui_enum.py
mangokit/exceptions/__init__.py
mangokit/exceptions/_error_msg.py
mangokit/exceptions/_exceptions.py
mangokit/log_collector/__init__.py
mangokit/log_collector/_log_control.py
mangokit/mangos/__init__.py
mangokit/mangos/pyarmor_runtime_linux/__init__.py
mangokit/mangos/pyarmor_runtime_linux/mango.py
mangokit/mangos/pyarmor_runtime_linux/pyarmor_runtime_000000/__init__.py
mangokit/mangos/pyarmor_runtime_linux/pyarmor_runtime_000000/pyarmor_runtime.so
mangokit/mangos/pyarmor_runtime_windows/__init__.py
mangokit/mangos/pyarmor_runtime_windows/mango.py
mangokit/mangos/pyarmor_runtime_windows/pyarmor_runtime_000000/__init__.py
mangokit/mangos/pyarmor_runtime_windows/pyarmor_runtime_000000/pyarmor_runtime.pyd
mangokit/models/__init__.py
mangokit/models/_models.py
mangokit/models/_ui_model.py
mangokit/notice/__init__.py
mangokit/notice/_mail_send.py
mangokit-2.6.22.dist-info/LICENSE
mangokit-2.6.22.dist-info/METADATA
mangokit-2.6.22.dist-info/WHEEL
mangokit-2.6.22.dist-info/top_level.txt
mangokit-2.6.22.dist-info/RECORD
