Metadata-Version: 2.1
Name: mangokit
Version: 2.6.22
Summary: 测试工具
Home-page: https://gitee.com/mao-peng/testkit
Author: 毛鹏
Author-email: 729164035@qq.com
Classifier: Programming Language :: Python :: 3.10
License-File: LICENSE
Requires-Dist: setuptools ==68.2.0
Requires-Dist: requests ==2.32.3
Requires-Dist: aiohttp ==3.10.11
Requires-Dist: aiomysql ==0.2.0
Requires-Dist: PyMySQL ==1.1.1
Requires-Dist: jsonpath ==0.82.2
Requires-Dist: cachetools ==5.3.1
Requires-Dist: Faker ==24.1.0
Requires-Dist: diskcache ==5.6.3
Requires-Dist: urllib3 ==2.2.3
Requires-Dist: pydantic ==2.9.2
Requires-Dist: colorlog ==6.7.0
Requires-Dist: pyarmor ==9.0.6
Requires-Dist: playwright ==1.43.0
Requires-Dist: uiautomation ==2.0.20
Requires-Dist: uiautomator2 ==3.2.5
Requires-Dist: assertpy ==1.1
Requires-Dist: deepdiff ==8.0.1
